README.md
setup.cfg
setup.py
sorcerer/__init__.py
sorcerer/__main__.py
sorcerer/cli.py
sorcerer/generator.py
sorcerer/scraper.py
sorcerer.egg-info/PKG-INFO
sorcerer.egg-info/SOURCES.txt
sorcerer.egg-info/dependency_links.txt
sorcerer.egg-info/entry_points.txt
sorcerer.egg-info/requires.txt
sorcerer.egg-info/top_level.txt
sorcerer/constants/__init__.py
sorcerer/constants/languages.py
sorcerer/constants/sites.py
sorcerer/utils/__init__.py
sorcerer/utils/get_slice_length.py
sorcerer/utils/list_tolower.py
tests/__init__.py
tests/test_get_slice_length.py
tests/test_list_tolower.py