Metadata-Version: 2.1
Name: sorcerer
Version: 0.11
Summary: Programming problem solution README table generator
Home-page: https://github.com/terror/sorcerer
Author: Liam Scalzulli
Author-email: liamscalzulli@gmail.com
License: UNKNOWN
Project-URL: Source Code, https://github.com/terror/sorcerer
Keywords: programming competitive tables markdown readmes
Platform: UNKNOWN
Classifier: Development Status :: 3 - Alpha
Classifier: License :: OSI Approved :: MIT License
Classifier: Programming Language :: Python
Classifier: Programming Language :: Python :: 3.7
Classifier: Programming Language :: Python :: 3.8
Classifier: Programming Language :: Python :: 3.9
Classifier: Programming Language :: Python :: 3 :: Only
Requires-Python: >=3.7
